README.md
setup.py
videdit/__init__.py
videdit/__main__.py
videdit/checks.py
videdit/commands.py
videdit/exceptions.py
videdit/parse.py
videdit/types.py
videdit.egg-info/PKG-INFO
videdit.egg-info/SOURCES.txt
videdit.egg-info/dependency_links.txt
videdit.egg-info/entry_points.txt
videdit.egg-info/top_level.txt