Metadata-Version: 2.1
Name: videdit
Version: 0.0.3
Summary: Set of commands used to edit video files
Home-page: UNKNOWN
License: UNKNOWN
Platform: UNKNOWN
